{
  "kind": "collectionType",
  "collectionName": "sponsors",
  "info": {
    "singularName": "sponsor",
    "pluralName": "sponsors",
    "displayName": "Sponsoren",
    "description": ""
  },
  "options": {
    "draftAndPublish": true
  },
  "pluginOptions": {},
  "attributes": {
    "name": {
      "type": "string",
      "required": true
    },
    "picture": {
      "type": "media",
      "multiple": false,
      "required": true,
      "allowedTypes": [
        "images"
      ]
    },
    "url": {
      "type": "string"
    },
    "show_on_page": {
      "type": "boolean",
      "default": true,
      "required": true
    },
    "type": {
      "type": "enumeration",
      "enum": [
        "regular_sponsor",
        "main_sponsor"
      ],
      "default": "regular_sponsor",
      "required": true
    }
  }
}
